mesh/__init__.py
mesh/logger.py
mesh/utils.py
mesh/dataframes/__init__.py
mesh/dataframes/row_operations.py
mesh/dataframes/validators.py
mesh/dates/__init__.py
mesh/dates/wrangler.py
mesh/google/__init__.py
mesh/google/gcs.py
spatialedge_analytics_mesh-0.0.2.data/data/LICENSE
spatialedge_analytics_mesh-0.0.2.dist-info/LICENSE
spatialedge_analytics_mesh-0.0.2.dist-info/METADATA
spatialedge_analytics_mesh-0.0.2.dist-info/WHEEL
spatialedge_analytics_mesh-0.0.2.dist-info/top_level.txt
spatialedge_analytics_mesh-0.0.2.dist-info/RECORD
