Metadata-Version: 2.1
Name: spatialedge-analytics-mesh
Version: 0.0.2
Summary: Facades and common functions necessary for data science and data engineering workflows
Home-page: UNKNOWN
Author: Jacques du Toit, Carl du Plessis, Lydia de Lange, Bernie Lindner
Author-email: 
License: UNKNOWN
Platform: UNKNOWN
Classifier: Environment :: Console
Classifier: Intended Audience :: Developers
Classifier: Programming Language :: Python :: 3
Classifier: Topic :: Scientific/Engineering :: Information Analysis
Classifier: Topic :: Utilities
Requires-Dist: coverage (>=4.5.4)
Requires-Dist: numpy (>=1.17.0)
Requires-Dist: pandas (>==1.1.3)
Requires-Dist: python-dateutil (>=2.8.0)
Requires-Dist: google-cloud-storage (>=1.24.1)
Requires-Dist: google-cloud-bigquery (>=2.2.0)
Requires-Dist: pytz (>=2019.2)
Requires-Dist: anybadge (>=1.7.0)
Requires-Dist: pylint (>=2.6.0)
Requires-Dist: pylint-exit (>=1.2.0)
